pytest_libnotify/__init__.py
pytest_libnotify-1.0.1.dist-info/METADATA
pytest_libnotify-1.0.1.dist-info/WHEEL
pytest_libnotify-1.0.1.dist-info/entry_points.txt
pytest_libnotify-1.0.1.dist-info/top_level.txt
pytest_libnotify-1.0.1.dist-info/RECORD
